<annotation>
	<folder>images</folder>
	<filename>n03538406_986.JPEG</filename>
	<path>Z:\LongAoTian\SpermSurvival\ultralytics\data\horse\images\n03538406_986.JPEG</path>
	<source>
		<database>Unknown</database>
	</source>
	<size>
		<width>500</width>
		<height>375</height>
		<depth>3</depth>
	</size>
	<segmented>0</segmented>
	<object>
		<name>horse</name>
		<pose>Unspecified</pose>
		<truncated>0</truncated>
		<difficult>1</difficult>
		<bndbox>
			<xmin>147</xmin>
			<ymin>158</ymin>
			<xmax>276</xmax>
			<ymax>352</ymax>
		</bndbox>
	</object>
	<object>
		<name>horse</name>
		<pose>Unspecified</pose>
		<truncated>0</truncated>
		<difficult>1</difficult>
		<bndbox>
			<xmin>213</xmin>
			<ymin>167</ymin>
			<xmax>345</xmax>
			<ymax>346</ymax>
		</bndbox>
	</object>
</annotation>
